[{"group_id":"100","name":"Test Workspace 1","groupReference":"Group ABC","groupMembers":[],"sections":[{"name":"research","artifacts":[{"type":"link","name":"GitHub","url":"https://github.com/hh11100/cm2020-agil-t3g4-wcm"},{"type":"link","name":"GitHub","url":"https://github.com/hh11100/cm2020-agil-t3g4-wcm"}]},{"name":"deliverables","artifacts":[]}]},{"group_id":"101","name":"Test Workspace 2","groupReference":"Group XYZ","groupMembers":[],"sections":[{"name":"research","artifacts":[]},{"name":"deliverables","artifacts":[]}]}]